CHANGES.txt
LICENSE.txt
MANIFEST
MANIFEST.in
README.md
setup.py
data/themes/clean/Vera.ttf
data/themes/clean/box.down.png
data/themes/clean/box.normal.png
data/themes/clean/button.down.png
data/themes/clean/button.normal.png
data/themes/clean/checkbox.off.normal.png
data/themes/clean/checkbox.on.down.png
data/themes/clean/checkbox.on.normal.png
data/themes/clean/console.input.focus.png
data/themes/clean/console.input.normal.png
data/themes/clean/console.png
data/themes/clean/desktop.png
data/themes/clean/dialog.bar.png
data/themes/clean/dialog.close.down.png
data/themes/clean/dialog.close.normal.png
data/themes/clean/dialog.png
data/themes/clean/filebrowser.folder.png
data/themes/clean/hslider.left.png
data/themes/clean/hslider.right.png
data/themes/clean/input.focus.png
data/themes/clean/input.normal.png
data/themes/clean/list.item.normal.png
data/themes/clean/list.png
data/themes/clean/menu.down.png
data/themes/clean/menu.hover.png
data/themes/clean/menu.normal.png
data/themes/clean/menu.option.hover.png
data/themes/clean/menu.option.normal.png
data/themes/clean/radio.off.normal.png
data/themes/clean/radio.on.down.png
data/themes/clean/radio.on.normal.png
data/themes/clean/select.arrow.down.png
data/themes/clean/select.arrow.normal.png
data/themes/clean/select.arrow.png
data/themes/clean/select.option.hover.png
data/themes/clean/select.option.normal.png
data/themes/clean/select.options.png
data/themes/clean/select.selected.normal.png
data/themes/clean/slider.bar.normal.png
data/themes/clean/slider.png
data/themes/clean/style.ini
data/themes/clean/tool.down.png
data/themes/clean/tool.normal.png
data/themes/clean/vslider.down.png
data/themes/clean/vslider.up.png
data/themes/default/Vera.ttf
data/themes/default/box.down.png
data/themes/default/box.hover.png
data/themes/default/box.normal.png
data/themes/default/box.xcf
data/themes/default/button.down.tga
data/themes/default/button.hover.tga
data/themes/default/button.normal.tga
data/themes/default/check.png
pygame_pgu.egg-info/PKG-INFO
pygame_pgu.egg-info/SOURCES.txt
pygame_pgu.egg-info/dependency_links.txt
pygame_pgu.egg-info/requires.txt
pygame_pgu.egg-info/top_level.txt
