Metadata-Version: 1.1
Name: pygame-pgu
Version: 0.21
Summary: Phil's pyGame Utilities - a collection of handy modules and scripts for PyGame.
Home-page: https://github.com/parogers/pgu
Author: Phil Hassey
Author-email: philhassey@yahoo.com
License: UNKNOWN
Project-URL: Source Code, https://github.com/parogers/pgu
Platform: UNKNOWN
Classifier: Development Status :: 5 - Production/Stable
Classifier: Intended Audience :: Developers
Classifier: Operating System :: MacOS :: MacOS X
Classifier: Operating System :: Microsoft :: Windows
Classifier: Operating System :: POSIX
Classifier: Programming Language :: Python
Classifier: Programming Language :: Python :: 3 :: Only
